slack_progress/__init__.py
slack_progress-0.5.dist-info/LICENSE
slack_progress-0.5.dist-info/METADATA
slack_progress-0.5.dist-info/WHEEL
slack_progress-0.5.dist-info/top_level.txt
slack_progress-0.5.dist-info/RECORD
