Metadata-Version: 2.1
Name: slack-progress
Version: 0.5
Summary: A realtime progress bar for Slack
Home-page: https://github.com/bcicen/slack-progress
Author: Bradley Cicenas
Author-email: bradley@vektor.nyc
License: http://opensource.org/licenses/MIT
Keywords: slack chatops devops
Platform: UNKNOWN
Classifier: Intended Audience :: Developers
Classifier: License :: OSI Approved :: MIT License
Classifier: Programming Language :: Python :: 2
Classifier: Programming Language :: Python :: 3
Requires-Dist: slacker (>=0.9.25)
